marcalyx/__init__.py
marcalyx/__version__.py
marcalyx/marcalyx.py
marcalyx-1.0.2.dist-info/METADATA
marcalyx-1.0.2.dist-info/WHEEL
marcalyx-1.0.2.dist-info/top_level.txt
marcalyx-1.0.2.dist-info/RECORD
