Metadata-Version: 2.1
Name: marcalyx
Version: 1.0.2
Summary: Simple python interface for reading MARC-XML
Home-page: https://github.com/seanredmond/marcalyx
Author: Sean Redmond
Author-email: github-smr@sneakemail.com
License: MIT
Platform: UNKNOWN
Classifier: License :: OSI Approved :: MIT License
Classifier: Programming Language :: Python
Requires-Python: >=2.7.0
Provides-Extra: dev
Requires-Dist: pytest ; extra == 'dev'
